Metadata-Version: 2.4
Name: llama-cancer
Version: 0.1.0
Summary: Tools and models for cancer research using LlamaAI components.
Project-URL: Homepage, https://github.com/yourusername/llama-cancer
Project-URL: Bug Tracker, https://github.com/yourusername/llama-cancer/issues
Author-email: Your Name <your.email@example.com>
License:                                  Apache License
License-File: LICENSE
Classifier: Development Status :: 3 - Alpha
Classifier: Intended Audience :: Developers
Classifier: Intended Audience :: Science/Research
Classifier: License :: OSI Approved :: MIT License
Classifier: Programming Language :: Python :: 3
Classifier: Programming Language :: Python :: 3.8
Classifier: Programming Language :: Python :: 3.9
Classifier: Programming Language :: Python :: 3.10
Classifier: Programming Language :: Python :: 3.11
Classifier: Topic :: Scientific/Engineering :: Artificial Intelligence
Classifier: Topic :: Scientific/Engineering :: Bio-Informatics
Requires-Python: >=3.8
Requires-Dist: adjusttext>=0.7.3
Requires-Dist: lifelines>=0.27
Requires-Dist: matplotlib>=3.5
Requires-Dist: ml-collections>=0.1.1
Requires-Dist: numpy>=1.22
Requires-Dist: openpyxl>=3.0
Requires-Dist: pandas>=1.4
Requires-Dist: pyyaml>=6.0
Requires-Dist: scikit-learn>=1.1
Requires-Dist: scipy>=1.8
Requires-Dist: seaborn>=0.12
Requires-Dist: statsmodels>=0.13
Requires-Dist: tqdm>=4.60
Provides-Extra: all
Requires-Dist: black>=23.3.0; extra == 'all'
Requires-Dist: isort>=5.12.0; extra == 'all'
Requires-Dist: mkdocs-material>=9.1.6; extra == 'all'
Requires-Dist: mkdocs>=1.4.2; extra == 'all'
Requires-Dist: mkdocstrings[python]>=0.20.0; extra == 'all'
Requires-Dist: mypy>=1.2.0; extra == 'all'
Requires-Dist: pre-commit>=3.3.1; extra == 'all'
Requires-Dist: pytest-cov; extra == 'all'
Requires-Dist: pytest-mock>=3.5; extra == 'all'
Requires-Dist: pytest>=7.0; extra == 'all'
Requires-Dist: ruff>=0.0.260; extra == 'all'
Provides-Extra: dev
Requires-Dist: black>=23.3.0; extra == 'dev'
Requires-Dist: isort>=5.12.0; extra == 'dev'
Requires-Dist: mypy>=1.2.0; extra == 'dev'
Requires-Dist: pre-commit>=3.3.1; extra == 'dev'
Requires-Dist: pytest-cov; extra == 'dev'
Requires-Dist: pytest-mock>=3.5; extra == 'dev'
Requires-Dist: pytest>=7.0; extra == 'dev'
Requires-Dist: ruff>=0.0.260; extra == 'dev'
Provides-Extra: docs
Requires-Dist: mkdocs-material>=9.1.6; extra == 'docs'
Requires-Dist: mkdocs>=1.4.2; extra == 'docs'
Requires-Dist: mkdocstrings[python]>=0.20.0; extra == 'docs'
